[
  {
    "author": {
      "email": "Cole82@yahoo.com",
      "nombre": "Ayla",
      "apellido": "Cummings",
      "edad": 61,
      "alias": "Gail_Klocko",
      "avatar": "https://cloudflare-ipfs.com/ipfs/Qmd3W5DuhgHirLHGVixi6V76LhCkZUz6pnFt5AJBiyvHye/avatar/113.jpg"
    },
    "comment": {
      "texto": "Repellat placeat ratione beatae ut voluptas reprehenderit facere qui. Non et nam. Ratione omnis illum hic vero voluptates qui tenetur quos debitis.",
      "_id": "94bdabede3e2deadaca4aba2"
    }
  }
]